utilitiez/ py.typed
utilitiez/__init__.py
utilitiez/_version.py
utilitiez/densityplot.py
utilitiez/mathematics/__init__.py
utilitiez/mathematics/misc.py
utilitiez/mathematics/xlogx.py
utilitiez-0.4.1.dist-info/licenses/LICENSE
utilitiez-0.4.1.dist-info/METADATA
utilitiez-0.4.1.dist-info/WHEEL
utilitiez-0.4.1.dist-info/top_level.txt
utilitiez-0.4.1.dist-info/RECORD
