Metadata-Version: 2.4
Name: utilitiez
Version: 0.4.1
Summary: Miscellaneous python utilities
Author-email: David Zwicker <david.zwicker@ds.mpg.de>
License: MIT
Project-URL: homepage, https://github.com/zwicker-group/utilitiez
Project-URL: repository, https://github.com/zwicker-group/utilitiez
Keywords: tools,utils
Classifier: Development Status :: 4 - Beta
Classifier: Intended Audience :: Developers
Classifier: Intended Audience :: Science/Research
Classifier: Topic :: Scientific/Engineering
Classifier: License :: OSI Approved :: MIT License
Classifier: Programming Language :: Python :: 3
Classifier: Programming Language :: Python :: 3.9
Classifier: Programming Language :: Python :: 3.10
Classifier: Programming Language :: Python :: 3.11
Classifier: Programming Language :: Python :: 3.12
Classifier: Programming Language :: Python :: 3.13
Requires-Python: <3.14,>=3.9
License-File: LICENSE
Requires-Dist: matplotlib>=3.1
Requires-Dist: numba>=0.45
Requires-Dist: numpy>=1.22
Requires-Dist: scipy>=1.5
Dynamic: license-file
